<!DOCTYPE ui:UiBinder SYSTEM "http://dl.google.com/gwt/DTD/xhtml.ent">
<ui:UiBinder xmlns:ui="urn:ui:com.google.gwt.uibinder"
	xmlns:g="urn:import:com.google.gwt.user.client.ui" 
	xmlns:cell="urn:import:com.google.gwt.user.cellview.client">

	<ui:style src="FullWidth.css" />

	<g:ScrollPanel addStyleNames="{style.fullpagecontainer}">
		<g:FlowPanel>
			<g:FlowPanel addStyleNames="{style.titlepanel}">
				<g:Button addStyleNames="{style.titlelogoutbutton}" ui:field="logoutButton" />
				<g:InlineLabel addStyleNames="{style.titleuserlabel}" ui:field="userInfoLabel" />
				<g:InlineLabel addStyleNames="{style.titlepagelabel}" ui:field="titleLabel" />
				<g:Label addStyleNames="{style.titlereset}" />
			</g:FlowPanel>
			<g:HTML addStyleNames="{style.introhtml}" ui:field="introHtml" />
			<cell:DataGrid addStyleNames="{style.addldocsgrid}" ui:field="addlDocsGrid" />
			<g:FormPanel ui:field="uploadForm">
				<g:FlowPanel>
					<g:FileUpload name="metadataupload" addStyleNames="{style.uploadfile}"
							ui:field="docUpload" />
					<g:Hidden name="timestamp" ui:field="timestampToken" /> 
					<g:Hidden name="expocodes" ui:field="expocodesToken" />
					<g:Hidden name="ometoken" ui:field="omeToken" />
				</g:FlowPanel>
			</g:FormPanel>
			<g:FlowPanel addStyleNames="{style.horizontalbuttonpanel}">
				<g:Button addStyleNames="{style.horizontalbutton}" ui:field="uploadButton" />
				<g:Button addStyleNames="{style.horizontalbutton}" ui:field="dismissButton" />
			</g:FlowPanel>
		</g:FlowPanel>
	</g:ScrollPanel>

</ui:UiBinder>
